{
  "db_name": "PostgreSQL",
  "query": "\n            INSERT INTO consultant_preferences (consultant_id, preferences, updated_at)\n            VALUES ($1, jsonb_build_object($2::text, $3::text), now())\n            ON CONFLICT (consultant_id)\n            DO UPDATE SET\n                preferences = consultant_preferences.preferences || jsonb_build_object($2::text, $3::text),\n                updated_at = now()\n            ",
  "describe": {
    "columns": [],
    "parameters": {
      "Left": [
        "Text",
        "Text",
        "Text"
      ]
    },
    "nullable": []
  },
  "hash": "98e1276d6fac7e78ba14eb216e14d8fb2a24048e6819b741800ea1cbe6a9cada"
}
